github_feedparser
