Metadata-Version: 1.1
Name: github-feedparser
Version: 0.1.1
Summary: Python module to parse a GitHub repository's Atom Feed
Home-page: https://github.com/wadewilliams/github-atom-feed-parser
Author: Wade Williams
Author-email: wade@wadewilliams.com
License: MIT
Download-URL: https://github.com/wadewilliams/github-atom-feed-parser/tarball/0.1
Keywords: github,rss,atom,feedparser
Platform: UNKNOWN
